{
  "$schema": "http://json-schema.org/draft-07/schema#",
  "title": "Batch API Types",
  "definitions": {
    "BatchConfig": {
      "properties": {
        "fields": {
          "items": {
            "type": "string"
          },
          "title": "Fields",
          "type": "array"
        }
      },
      "required": [
        "fields"
      ],
      "title": "BatchConfig",
      "type": "object"
    },
    "BatchCreate": {
      "properties": {
        "custom_name": {
          "title": "Custom Name",
          "type": "string"
        },
        "session_id": {
          "title": "Session Id",
          "type": "string"
        },
        "fields": {
          "anyOf": [
            {
              "items": {
                "type": "string"
              },
              "type": "array"
            },
            {
              "type": "null"
            }
          ],
          "default": null,
          "title": "Fields"
        }
      },
      "required": [
        "custom_name",
        "session_id"
      ],
      "title": "BatchCreate",
      "type": "object"
    },
    "BatchResponse": {
      "properties": {
        "batch_name": {
          "title": "Batch Name",
          "type": "string"
        },
        "status": {
          "title": "Status",
          "type": "string"
        },
        "files_count": {
          "title": "Files Count",
          "type": "integer"
        }
      },
      "required": [
        "batch_name",
        "status",
        "files_count"
      ],
      "title": "BatchResponse",
      "type": "object"
    },
    "BatchHistory": {
      "properties": {
        "batch_name": {
          "title": "Batch Name",
          "type": "string"
        },
        "status": {
          "title": "Status",
          "type": "string"
        },
        "created_at": {
          "title": "Created At",
          "type": "string"
        },
        "files_count": {
          "title": "Files Count",
          "type": "integer"
        },
        "fields": {
          "items": {
            "type": "string"
          },
          "title": "Fields",
          "type": "array"
        }
      },
      "required": [
        "batch_name",
        "status",
        "created_at",
        "files_count",
        "fields"
      ],
      "title": "BatchHistory",
      "type": "object"
    },
    "ExtractionResult": {
      "properties": {
        "filename": {
          "title": "Filename",
          "type": "string"
        },
        "batch": {
          "title": "Batch",
          "type": "string"
        },
        "success": {
          "title": "Success",
          "type": "boolean"
        },
        "data": {
          "anyOf": [
            {
              "additionalProperties": {
                "type": "string"
              },
              "type": "object"
            },
            {
              "type": "null"
            }
          ],
          "default": null,
          "title": "Data"
        },
        "error": {
          "anyOf": [
            {
              "type": "string"
            },
            {
              "type": "null"
            }
          ],
          "default": null,
          "title": "Error"
        },
        "duration": {
          "title": "Duration",
          "type": "number"
        }
      },
      "required": [
        "filename",
        "batch",
        "success",
        "duration"
      ],
      "title": "ExtractionResult",
      "type": "object"
    }
  }
}